_flake8_action_hero_version.py
flake8_action_hero/__init__.py
flake8_action_hero/actions/__init__.py
flake8_action_hero/actions/base.py
flake8_action_hero/actions/date.py
flake8_action_hero/actions/package.py
flake8_action_hero/checker.py
flake8_action_hero/enums.py
flake8_action_hero/metadata.py
flake8_action_hero-0.1.1.dist-info/entry_points.txt
flake8_action_hero-0.1.1.dist-info/LICENSE
flake8_action_hero-0.1.1.dist-info/WHEEL
flake8_action_hero-0.1.1.dist-info/METADATA
flake8_action_hero-0.1.1.dist-info/RECORD
