Metadata-Version: 2.1
Name: flake8-action-hero
Version: 0.1.1
Summary: A plugin for flake8 that performs conditional FIXME/TODO checks.
Home-page: https://github.com/whardier/flake8-action-hero
License: MIT
Keywords: flake8,plugin,linting,code quality,quality assurance
Author: Shane Spencer
Author-email: 305301+whardier@users.noreply.github.com 
Requires-Python: >=3.8,<4.0
Classifier: Development Status :: 5 - Production/Stable
Classifier: Environment :: Console
Classifier: Framework :: Flake8
Classifier: Intended Audience :: Developers
Classifier: License :: OSI Approved :: MIT License
Classifier: Operating System :: OS Independent
Classifier: Programming Language :: Python :: 3
Classifier: Programming Language :: Python :: 3.8
Classifier: Programming Language :: Python :: 3.9
Classifier: Topic :: Software Development :: Libraries :: Python Modules
Classifier: Topic :: Software Development :: Quality Assurance
Provides-Extra: package
Requires-Dist: flake8 (>=3.9.2,<4.0.0)
Requires-Dist: importlib-metadata (>=4.6.3,<5.0.0); extra == "package"
Requires-Dist: packages (>=0.1.0,<0.2.0); extra == "package"
Project-URL: Repository, https://github.com/whardier/flake8-action-hero
